appserver_sdk_python_i18n_pt_br/__init__.py
appserver_sdk_python_i18n_pt_br/validation/__init__.py
appserver_sdk_python_i18n_pt_br/validation/cnpj.py
appserver_sdk_python_i18n_pt_br/validation/cpf.py
appserver_sdk_python_i18n_pt_br-0.1.4.dist-info/LICENSE
appserver_sdk_python_i18n_pt_br-0.1.4.dist-info/METADATA
appserver_sdk_python_i18n_pt_br-0.1.4.dist-info/WHEEL
appserver_sdk_python_i18n_pt_br-0.1.4.dist-info/RECORD
