Metadata-Version: 2.3
Name: appserver-sdk-python-i18n-pt-br
Version: 0.1.4
Summary: Brazilian Portuguese Utilities for Python
License: MIT
Keywords: validação,cpf,cnpj
Author: Appserver SDK
Author-email: suporte@apppserver.com.br
Requires-Python: >=3.11
Classifier: Development Status :: 4 - Beta
Classifier: Intended Audience :: Developers
Classifier: License :: OSI Approved :: MIT License
Classifier: Programming Language :: Python :: 3
Classifier: Programming Language :: Python :: 3.11
Classifier: Programming Language :: Python :: 3.12
Classifier: Programming Language :: Python :: 3.13
Project-URL: Documentation, https://github.com/appserver-sdk/python-i18n-pt-br#readme
Project-URL: Homepage, https://github.com/appserver-sdk/python-i18n-pt-br
Project-URL: Issues, https://github.com/appserver-sdk/python-i18n-pt-br/issues
Project-URL: Repository, https://github.com/appserver-sdk/python-i18n-pt-br
